banco_dados/__init__.py
banco_dados/connection.py
banco_dados/delete_bd.py
banco_dados/insert_bd.py
banco_dados/select_bd.py
banco_dados/update_bd.py
banco_dados/utils.py
banco_dados-0.1.0.dist-info/METADATA
banco_dados-0.1.0.dist-info/WHEEL
banco_dados-0.1.0.dist-info/top_level.txt
banco_dados-0.1.0.dist-info/RECORD
